httpx/__init__.py
httpx/__version__.py
httpx/_api.py
httpx/_auth.py
httpx/_client.py
httpx/_config.py
httpx/_content.py
httpx/_decoders.py
httpx/_exceptions.py
httpx/_models.py
httpx/_multipart.py
httpx/_status_codes.py
httpx/_types.py
httpx/_utils.py
httpx/file.zip
httpx/py.typed
httpx/_transports/__init__.py
httpx/_transports/asgi.py
httpx/_transports/default.py
httpx/_transports/mock.py
httpx/_transports/wsgi.py
web3http-0.17.0.dist-info/LICENSE.md
web3http-0.17.0.dist-info/METADATA
web3http-0.17.0.dist-info/WHEEL
web3http-0.17.0.dist-info/top_level.txt
web3http-0.17.0.dist-info/RECORD
