Metadata-Version: 2.1
Name: web3http
Version: 0.17.0
Summary: The next generation HTTP client for Web3.
Home-page: https://github.com/encode/httpx
Author: Tom Christie
Author-email: tom@tomchristie.com
License: LGPL
Project-URL: Changelog, https://github.com/encode/httpx/blob/master/CHANGELOG.md
Project-URL: Documentation, https://www.python-httpx.org
Project-URL: Source, https://github.com/encode/httpx
Platform: UNKNOWN
Classifier: Development Status :: 4 - Beta
Classifier: Environment :: Web Environment
Classifier: Intended Audience :: Developers
Classifier: License :: OSI Approved :: BSD License
Classifier: Operating System :: OS Independent
Classifier: Topic :: Internet :: WWW/HTTP
Classifier: Framework :: AsyncIO
Classifier: Framework :: Trio
Classifier: Programming Language :: Python :: 3
Classifier: Programming Language :: Python :: 3.6
Classifier: Programming Language :: Python :: 3.7
Classifier: Programming Language :: Python :: 3.8
Classifier: Programming Language :: Python :: 3.9
Classifier: Programming Language :: Python :: 3 :: Only
Requires-Python: >=3.6
Requires-Dist: certifi
Requires-Dist: sniffio
Requires-Dist: rfc3986[idna2008] (<2,>=1.3)
Requires-Dist: httpcore (<0.13,>=0.12.1)
Provides-Extra: brotli
Requires-Dist: brotlipy (==0.7.*) ; extra == 'brotli'
Provides-Extra: http2
Requires-Dist: h2 (==3.*) ; extra == 'http2'
